zero_trust/__init__.py
zero_trust/auth.py
zero_trust/client.py
zero_trust/config.py
zero_trust/database.py
zero_trust/http_client.py
zero_trust/migration.py
zero_trust/sync.py
zero_trust/types.py
zero_trust_sdk-0.1.0.dist-info/METADATA
zero_trust_sdk-0.1.0.dist-info/WHEEL
zero_trust_sdk-0.1.0.dist-info/top_level.txt
zero_trust_sdk-0.1.0.dist-info/RECORD
