Metadata-Version: 2.4
Name: zero-trust-sdk
Version: 0.1.0
Summary: Python SDK for Zero Trust Blockchain Database - Secure, programmable access to zero-trust data storage with pandas integration
Author-email: Zero Trust Team <dev@zerotrust.com>
Project-URL: Homepage, https://zerotrust.com
Project-URL: Documentation, https://docs.zerotrust.com/python-sdk
Project-URL: Repository, https://github.com/your-org/zero-trust-python-sdk
Project-URL: Bug Tracker, https://github.com/your-org/zero-trust-python-sdk/issues
Keywords: database,blockchain,zero-trust,sdk,pandas,dataframe
Classifier: Development Status :: 4 - Beta
Classifier: Intended Audience :: Developers
Classifier: License :: OSI Approved :: MIT License
Classifier: Operating System :: OS Independent
Classifier: Programming Language :: Python :: 3
Classifier: Programming Language :: Python :: 3.8
Classifier: Programming Language :: Python :: 3.9
Classifier: Programming Language :: Python :: 3.10
Classifier: Programming Language :: Python :: 3.11
Classifier: Programming Language :: Python :: 3.12
Classifier: Topic :: Database
Classifier: Topic :: Software Development :: Libraries :: Python Modules
Requires-Python: >=3.8
Requires-Dist: requests>=2.28.0
Requires-Dist: pandas>=1.3.0
Requires-Dist: numpy>=1.20.0
Requires-Dist: typing-extensions>=4.0.0; python_version < "3.10"
Provides-Extra: dev
Requires-Dist: pytest>=7.0.0; extra == "dev"
Requires-Dist: pytest-cov>=4.0.0; extra == "dev"
Requires-Dist: pytest-asyncio>=0.21.0; extra == "dev"
Requires-Dist: black>=22.0.0; extra == "dev"
Requires-Dist: isort>=5.10.0; extra == "dev"
Requires-Dist: flake8>=5.0.0; extra == "dev"
Requires-Dist: mypy>=1.0.0; extra == "dev"
Requires-Dist: pre-commit>=2.20.0; extra == "dev"
Provides-Extra: async
Requires-Dist: aiohttp>=3.8.0; extra == "async"
Requires-Dist: asyncio>=3.4.3; extra == "async"
Provides-Extra: visualization
Requires-Dist: matplotlib>=3.5.0; extra == "visualization"
Requires-Dist: seaborn>=0.11.0; extra == "visualization"
Requires-Dist: plotly>=5.0.0; extra == "visualization"
Provides-Extra: jupyter
Requires-Dist: jupyter>=1.0.0; extra == "jupyter"
Requires-Dist: ipywidgets>=7.6.0; extra == "jupyter"
Provides-Extra: all
Requires-Dist: zero-trust-sdk[async,dev,jupyter,visualization]; extra == "all"
